{
  "type": "system",
  "name": "MockSystem",
  "tags": [
    "dobre"
  ],
  "properties": [
    {
      "name": "bravo ve lud male kolko sum gotin",
      "value": "propertySelection"
    },
    {
      "name": "hmmmm",
      "value": "uses"
    }
  ],
  "categories": [
    {
      "name": "Tova mi e purvata kategoriq type shi on god",
      "propertyKeys": [
        "bravo ve lud male kolko sum gotin",
        "hmmmm"
      ],
      "items": [
        {
          "name": "New Item",
          "maxTier": 1,
          "properties": {
            "bravo ve lud male kolko sum gotin": "",
            "hmmmm": ""
          }
        }
      ],
      "showProps": true,
      "minimized": false
    }
  ],
  "sheetStructure": {
    "lg": [
      {
        "i": "Sample Window",
        "x": 0,
        "y": 0,
        "w": 1,
        "h": 1,
        "moved": false,
        "static": false,
        "isDraggable": true,
        "isResizable": true
      }
    ]
  }
}